README.md
setup.py
rajjix/__init__.py
rajjix/tools.py
rajjix_tools.egg-info/PKG-INFO
rajjix_tools.egg-info/SOURCES.txt
rajjix_tools.egg-info/dependency_links.txt
rajjix_tools.egg-info/top_level.txt